process_ble_data/__init__.py
process_ble_data/honeycomb_io.py
wf_process_ble_data-0.0.1.dist-info/LICENSE
wf_process_ble_data-0.0.1.dist-info/METADATA
wf_process_ble_data-0.0.1.dist-info/WHEEL
wf_process_ble_data-0.0.1.dist-info/top_level.txt
wf_process_ble_data-0.0.1.dist-info/RECORD
